diffjeom/__init__.py
diffjeom/diffjeom.py
diffjeom-0.0.1.dist-info/LICENSE
diffjeom-0.0.1.dist-info/METADATA
diffjeom-0.0.1.dist-info/WHEEL
diffjeom-0.0.1.dist-info/top_level.txt
diffjeom-0.0.1.dist-info/RECORD
