Metadata-Version: 2.1
Name: diffjeom
Version: 0.0.1
Summary: Differential geometry with jax
Home-page: https://github.com/adam-coogan/diffjeom
Author: Adam Coogan
Author-email: dr.adam.coogan@gmail.com
License: UNKNOWN
Project-URL: Bug Tracker, https://github.com/adam-coogan/diffjeom/issues
Keywords: differential geometry,jax
Platform: UNKNOWN
Classifier: Programming Language :: Python :: 3
Classifier: License :: OSI Approved :: MIT License
Classifier: Operating System :: OS Independent
Requires-Python: >=3.6
Requires-Dist: numpy
Requires-Dist: jax
Requires-Dist: jaxlib
